adb_screencap_streaming/LICENSE
adb_screencap_streaming/README.MD
adb_screencap_streaming/__init__.py
adb_screencap_streaming/requirements.txt
adb_screencap_streaming/thirdparty.json
adb_screencap_streaming-0.12.dist-info/LICENSE.rst
adb_screencap_streaming-0.12.dist-info/METADATA
adb_screencap_streaming-0.12.dist-info/WHEEL
adb_screencap_streaming-0.12.dist-info/top_level.txt
adb_screencap_streaming-0.12.dist-info/RECORD
