Metadata-Version: 2.1
Name: adb-screencap-streaming
Version: 0.12
Summary: Streams ADB's Screencap (useful for bots and video capturing)
Home-page: https://github.com/hansalemaos/adb_screencap_streaming
Author: Johannes Fischer
Author-email: <aulasparticularesdealemaosp@gmail.com>
License: MIT
Keywords: openCV,adb,screencap,android,bot,video,streaming
Classifier: Development Status :: 4 - Beta
Classifier: Programming Language :: Python :: 3 :: Only
Classifier: Programming Language :: Python :: 3.9
Classifier: Topic :: Scientific/Engineering :: Visualization
Classifier: Topic :: Software Development :: Libraries :: Python Modules
Classifier: Topic :: Text Editors :: Text Processing
Classifier: Topic :: Text Processing :: General
Classifier: Topic :: Text Processing :: Indexing
Classifier: Topic :: Text Processing :: Filters
Classifier: Topic :: Utilities
License-File: LICENSE.rst
Requires-Dist: a-cv2-easy-resize
Requires-Dist: keyboard
Requires-Dist: numpy
Requires-Dist: opencv-python
Requires-Dist: psutil
